acdcli-0.3.2.data/scripts/acd_cli.py
acdcli-0.3.2.dist-info/DESCRIPTION.rst
acdcli-0.3.2.dist-info/entry_points.txt
acdcli-0.3.2.dist-info/WHEEL
acdcli-0.3.2.dist-info/metadata.json
acdcli-0.3.2.dist-info/top_level.txt
acdcli-0.3.2.dist-info/RECORD
acdcli-0.3.2.dist-info/METADATA
acdcli/acd_fuse.py
acdcli/__init__.py
acdcli/plugins/template.py
acdcli/plugins/tou.py
acdcli/plugins/debug.py
acdcli/plugins/__init__.py
acdcli/utils/progress.py
acdcli/utils/threading.py
acdcli/utils/__init__.py
acdcli/utils/conf.py
acdcli/utils/time.py
acdcli/utils/hashing.py
acdcli/api/content.py
acdcli/api/common.py
acdcli/api/client.py
acdcli/api/metadata.py
acdcli/api/backoff_req.py
acdcli/api/oauth.py
acdcli/api/__init__.py
acdcli/api/account.py
acdcli/api/trash.py
acdcli/cache/format.py
acdcli/cache/cursors.py
acdcli/cache/db.py
acdcli/cache/sync.py
acdcli/cache/__init__.py
acdcli/cache/query.py
acdcli/cache/schema.py
