Metadata-Version: 2.0
Name: acdcli
Version: 0.3.2
Summary: a command line interface and FUSE filesystem for Amazon Cloud Drive
Home-page: https://github.com/yadayada/acd_cli
Author: yadayada
Author-email: acd_cli@mail.com
License: GPLv2+
Download-URL: https://github.com/yadayada/acd_cli/tarball/0.3.2
Keywords: amazon cloud drive,clouddrive,FUSE
Platform: UNKNOWN
Classifier: Environment :: Console
Classifier: License :: OSI Approved :: GNU General Public License v2 or later (GPLv2+)
Classifier: Programming Language :: Python :: 3
Classifier: Programming Language :: Python :: 3.2
Classifier: Programming Language :: Python :: 3.3
Classifier: Programming Language :: Python :: 3.4
Classifier: Programming Language :: Python :: 3.5
Classifier: Programming Language :: Python :: 3 :: Only
Classifier: Development Status :: 4 - Beta
Classifier: Topic :: System :: Archiving :: Backup
Classifier: Topic :: System :: Filesystems
Requires-Dist: appdirs
Requires-Dist: colorama
Requires-Dist: fusepy
Requires-Dist: python-dateutil
Requires-Dist: requests (>=2.1.0,!=2.9.0)
Requires-Dist: requests-toolbelt (!=0.5.0)
Provides-Extra: docs
Requires-Dist: sphinx-paramlinks; extra == 'docs'
